detecteff_python-0.1.dist-info/METADATA
detecteff_python-0.1.dist-info/WHEEL
detecteff_python-0.1.dist-info/entry_points.txt
detecteff_python-0.1.dist-info/license_files/LICENSE
detecteff/__init__.py
detecteff/core.py
detecteff/rust.cpython-312-darwin.so
detecteff_python-0.1.dist-info/RECORD
