Metadata-Version: 2.3
Name: detecteff-python
Version: 0.1
Requires-Dist: argpi
License-File: LICENSE
Summary: Find and delete duplicate files!
Project-URL: GitHub, https://github.com/d33pster/detecteff-python
